{"result":{"parties":[],"classType":"Criminal","showRssButton":true,"receivables":[{"amountDue":889.32,"atCollections":false,"key":"53-529808","adjust":-187.85,"rcvblNo":529808,"countyNo":53,"probAmt":0.00,"paid":636.00,"dueDate":"2016-04-26","type":"R","atSdc":true,"balanceDue":65.47},{"amountDue":15.06,"atCollections":false,"key":"53-539495","adjust":4.56,"rcvblNo":539495,"countyNo":53,"probAmt":0.00,"paid":0.00,"dueDate":"2016-01-07","type":"R","atSdc":false,"balanceDue":19.62},{"amountDue":35.00,"atCollections":false,"key":"53-545889","adjust":-35.00,"rcvblNo":545889,"countyNo":53,"probAmt":0.00,"paid":0.00,"dueDate":null,"type":"R","atSdc":false,"balanceDue":0.00}],"countyName":"Rock","isReopenedRemandedFromAppeal":false,"daCaseNo":"2015RO005142","activities":[],"payplanLink":null,"chargeHist":[],"prosAtty":"Buker, Katharine","maintenance":null,"caseNo":"2015CM001960","execSummary":"<p data-section-name=\"guiltyPreamble\">\n    The defendant Kevin Lee Holton was found guilty\n    of the following <nobr>charge(s)</nobr> in this case.\n    \n    \n  </p><ul><li><div data-section-name=\"guiltyCriminal\">\n    <span class=\"leadIn\"/>\n    Obstructing an Officer,\n    a class A misdemeanor,\n    Wisconsin Statutes\n    946.41(1).\n  </div></li><li><div data-section-name=\"guiltyCriminal\">\n    <span class=\"leadIn\"/>\n    Carry Concealed Weapon,\n    a class A misdemeanor,\n    Wisconsin Statutes\n    941.23(2).\n  </div></li></ul><p data-section-name=\"notice\">\n    <strong>Notice to employers:</strong> It may be a violation of state law to\n    discriminate against a job applicant because of an arrest or conviction\n    record.  Generally speaking, an employer may refuse to hire an applicant on\n    the basis of a conviction only if the circumstances of the conviction\n    substantially relate to the particular job. For more information, see\n    <a href=\"http://docs.legis.wisconsin.gov/statutes/statutes/111/II/335\" rel=\"noopener noreferrer\" target=\"_blank\">Wisconsin Statute 111.335</a>\n    and the Department of Workforce Development's publication,\n    <cite><a href=\"https://dwd.wisconsin.gov/er/civilrights/discrimination/arrest.htm\" rel=\"noopener noreferrer\" target=\"_blank\">Arrest and Conviction Records under the Law</a></cite>.\n  </p>","warrants":[],"civilJdgmts":[{"dateDkted":"2016-04-26","satisfaction":"No","parties":[{"name":"Kevin Lee Holton","bankrupt":false,"released":false,"descr":"Debtor","centralAtty":null,"proHacVice":null,"key":"d3da0217b97c0d2e3a5bf70d65ea736db25f4bd3-1","status":"Active","address":"2139 Lenox Street, Beloit, WI 53511"},{"name":"Rock County Clerk of Circuit Court","bankrupt":null,"released":false,"descr":"Creditor","centralAtty":null,"proHacVice":null,"key":"d3da0217b97c0d2e3a5bf70d65ea736db25f4bd3-2","status":"Active","address":null}],"jdgmtDate":"2016-04-26","propDescr":null,"descr":"Judgment for money","typeOfTax":null,"amount":951.47,"key":"d3da0217b97c0d2e3a5bf70d65ea736db25f4bd3","svcDateTo":null,"cvJdgmtEvTypeDescr":null,"svcDateFrom":null,"multiple":false,"fullSatisDate":null,"dktedTime":"11:44 am","dbtrName":"Holton, Kevin Lee","warrantNo":null,"events":[],"amounts":[{"key":"d3da0217b97c0d2e3a5bf70d65ea736db25f4bd3-1","descr":"Judgment amount","amount":886.00},{"key":"d3da0217b97c0d2e3a5bf70d65ea736db25f4bd3-2","descr":"Post-judgment interest","amount":3.32},{"key":"d3da0217b97c0d2e3a5bf70d65ea736db25f4bd3-3","descr":"Post-judgment interest","amount":3.32},{"key":"d3da0217b97c0d2e3a5bf70d65ea736db25f4bd3-4","descr":"Post-judgment interest","amount":3.32},{"key":"d3da0217b97c0d2e3a5bf70d65ea736db25f4bd3-5","descr":"Post-judgment interest","amount":3.32},{"key":"d3da0217b97c0d2e3a5bf70d65ea736db25f4bd3-6","descr":"Post-judgment interest","amount":3.32},{"key":"d3da0217b97c0d2e3a5bf70d65ea736db25f4bd3-7","descr":"Post-judgment interest","amount":3.32},{"key":"d3da0217b97c0d2e3a5bf70d65ea736db25f4bd3-8","descr":"Post-judgment interest","amount":3.32},{"key":"d3da0217b97c0d2e3a5bf70d65ea736db25f4bd3-9","descr":"Post-judgment interest","amount":3.32},{"key":"d3da0217b97c0d2e3a5bf70d65ea736db25f4bd3-10","descr":"Post-judgment interest","amount":3.32},{"key":"d3da0217b97c0d2e3a5bf70d65ea736db25f4bd3-11","descr":"Post-judgment interest","amount":3.32},{"key":"d3da0217b97c0d2e3a5bf70d65ea736db25f4bd3-12","descr":"Post-judgment interest","amount":3.32},{"key":"d3da0217b97c0d2e3a5bf70d65ea736db25f4bd3-13","descr":"Post-judgment interest","amount":3.32},{"key":"d3da0217b97c0d2e3a5bf70d65ea736db25f4bd3-14","descr":"Post-judgment interest","amount":3.32},{"key":"d3da0217b97c0d2e3a5bf70d65ea736db25f4bd3-15","descr":"Post-judgment interest","amount":3.32},{"key":"d3da0217b97c0d2e3a5bf70d65ea736db25f4bd3-16","descr":"Post-judgment interest","amount":3.32},{"key":"d3da0217b97c0d2e3a5bf70d65ea736db25f4bd3-17","descr":"Post-judgment interest","amount":3.32},{"key":"d3da0217b97c0d2e3a5bf70d65ea736db25f4bd3-18","descr":"Post-judgment interest","amount":3.32},{"key":"d3da0217b97c0d2e3a5bf70d65ea736db25f4bd3-19","descr":"Post-judgment interest","amount":3.32},{"key":"d3da0217b97c0d2e3a5bf70d65ea736db25f4bd3-20","descr":"Post-judgment interest","amount":3.32},{"key":"d3da0217b97c0d2e3a5bf70d65ea736db25f4bd3-21","descr":"Post-judgment interest","amount":2.39}]},{"dateDkted":"2016-04-26","satisfaction":"No","parties":[{"name":"Kevin Lee Holton","bankrupt":false,"released":false,"descr":"Debtor","centralAtty":null,"proHacVice":null,"key":"697eb2550729a10ce9f1feb05a88200c975665a1-1","status":"Active","address":"2139 Lenox Street, Beloit, WI 53511"},{"name":"Rock County Clerk of Circuit Court","bankrupt":null,"released":false,"descr":"Creditor","centralAtty":null,"proHacVice":null,"key":"697eb2550729a10ce9f1feb05a88200c975665a1-2","status":"Active","address":null}],"jdgmtDate":"2016-04-26","propDescr":null,"descr":"Judgment for money","typeOfTax":null,"amount":19.62,"key":"697eb2550729a10ce9f1feb05a88200c975665a1","svcDateTo":null,"cvJdgmtEvTypeDescr":null,"svcDateFrom":null,"multiple":false,"fullSatisDate":null,"dktedTime":"11:45 am","dbtrName":"Holton, Kevin Lee","warrantNo":null,"events":[],"amounts":[{"key":"697eb2550729a10ce9f1feb05a88200c975665a1-1","descr":"Judgment amount","amount":15.00},{"key":"697eb2550729a10ce9f1feb05a88200c975665a1-2","descr":"Post-judgment interest","amount":0.06},{"key":"697eb2550729a10ce9f1feb05a88200c975665a1-3","descr":"Post-judgment interest","amount":0.06},{"key":"697eb2550729a10ce9f1feb05a88200c975665a1-4","descr":"Post-judgment interest","amount":0.06},{"key":"697eb2550729a10ce9f1feb05a88200c975665a1-5","descr":"Post-judgment interest","amount":0.06},{"key":"697eb2550729a10ce9f1feb05a88200c975665a1-6","descr":"Post-judgment interest","amount":0.06},{"key":"697eb2550729a10ce9f1feb05a88200c975665a1-7","descr":"Post-judgment interest","amount":0.06},{"key":"697eb2550729a10ce9f1feb05a88200c975665a1-8","descr":"Post-judgment interest","amount":0.06},{"key":"697eb2550729a10ce9f1feb05a88200c975665a1-9","descr":"Post-judgment interest","amount":0.06},{"key":"697eb2550729a10ce9f1feb05a88200c975665a1-10","descr":"Post-judgment interest","amount":0.06},{"key":"697eb2550729a10ce9f1feb05a88200c975665a1-11","descr":"Post-judgment interest","amount":0.06},{"key":"697eb2550729a10ce9f1feb05a88200c975665a1-12","descr":"Post-judgment interest","amount":0.06},{"key":"697eb2550729a10ce9f1feb05a88200c975665a1-13","descr":"Post-judgment interest","amount":0.06},{"key":"697eb2550729a10ce9f1feb05a88200c975665a1-14","descr":"Post-judgment interest","amount":0.06},{"key":"697eb2550729a10ce9f1feb05a88200c975665a1-15","descr":"Post-judgment interest","amount":0.06},{"key":"697eb2550729a10ce9f1feb05a88200c975665a1-16","descr":"Post-judgment interest","amount":0.06},{"key":"697eb2550729a10ce9f1feb05a88200c975665a1-17","descr":"Post-judgment interest","amount":0.06},{"key":"697eb2550729a10ce9f1feb05a88200c975665a1-18","descr":"Post-judgment interest","amount":0.06},{"key":"697eb2550729a10ce9f1feb05a88200c975665a1-19","descr":"Post-judgment interest","amount":0.06},{"key":"697eb2550729a10ce9f1feb05a88200c975665a1-20","descr":"Post-judgment interest","amount":0.06},{"key":"697eb2550729a10ce9f1feb05a88200c975665a1-21","descr":"Post-judgment interest","amount":0.06},{"key":"697eb2550729a10ce9f1feb05a88200c975665a1-22","descr":"Post-judgment interest","amount":0.06},{"key":"697eb2550729a10ce9f1feb05a88200c975665a1-23","descr":"Post-judgment interest","amount":0.06},{"key":"697eb2550729a10ce9f1feb05a88200c975665a1-24","descr":"Post-judgment interest","amount":0.06},{"key":"697eb2550729a10ce9f1feb05a88200c975665a1-25","descr":"Post-judgment interest","amount":0.06},{"key":"697eb2550729a10ce9f1feb05a88200c975665a1-26","descr":"Post-judgment interest","amount":0.06},{"key":"697eb2550729a10ce9f1feb05a88200c975665a1-27","descr":"Post-judgment interest","amount":0.06},{"key":"697eb2550729a10ce9f1feb05a88200c975665a1-28","descr":"Post-judgment interest","amount":0.06},{"key":"697eb2550729a10ce9f1feb05a88200c975665a1-29","descr":"Post-judgment interest","amount":0.06},{"key":"697eb2550729a10ce9f1feb05a88200c975665a1-30","descr":"Post-judgment interest","amount":0.06},{"key":"697eb2550729a10ce9f1feb05a88200c975665a1-31","descr":"Post-judgment interest","amount":0.06},{"key":"697eb2550729a10ce9f1feb05a88200c975665a1-32","descr":"Post-judgment interest","amount":0.06},{"key":"697eb2550729a10ce9f1feb05a88200c975665a1-33","descr":"Post-judgment interest","amount":0.06},{"key":"697eb2550729a10ce9f1feb05a88200c975665a1-34","descr":"Post-judgment interest","amount":0.06},{"key":"697eb2550729a10ce9f1feb05a88200c975665a1-35","descr":"Post-judgment interest","amount":0.06},{"key":"697eb2550729a10ce9f1feb05a88200c975665a1-36","descr":"Post-judgment interest","amount":0.06},{"key":"697eb2550729a10ce9f1feb05a88200c975665a1-37","descr":"Post-judgment interest","amount":0.06},{"key":"697eb2550729a10ce9f1feb05a88200c975665a1-38","descr":"Post-judgment interest","amount":0.06},{"key":"697eb2550729a10ce9f1feb05a88200c975665a1-39","descr":"Post-judgment interest","amount":0.06},{"key":"697eb2550729a10ce9f1feb05a88200c975665a1-40","descr":"Post-judgment interest","amount":0.06},{"key":"697eb2550729a10ce9f1feb05a88200c975665a1-41","descr":"Post-judgment interest","amount":0.06},{"key":"697eb2550729a10ce9f1feb05a88200c975665a1-42","descr":"Post-judgment interest","amount":0.06},{"key":"697eb2550729a10ce9f1feb05a88200c975665a1-43","descr":"Post-judgment interest","amount":0.06},{"key":"697eb2550729a10ce9f1feb05a88200c975665a1-44","descr":"Post-judgment interest","amount":0.06},{"key":"697eb2550729a10ce9f1feb05a88200c975665a1-45","descr":"Post-judgment interest","amount":0.06},{"key":"697eb2550729a10ce9f1feb05a88200c975665a1-46","descr":"Post-judgment interest","amount":0.06},{"key":"697eb2550729a10ce9f1feb05a88200c975665a1-47","descr":"Post-judgment interest","amount":0.06},{"key":"697eb2550729a10ce9f1feb05a88200c975665a1-48","descr":"Post-judgment interest","amount":0.06},{"key":"697eb2550729a10ce9f1feb05a88200c975665a1-49","descr":"Post-judgment interest","amount":0.06},{"key":"697eb2550729a10ce9f1feb05a88200c975665a1-50","descr":"Post-judgment interest","amount":0.06},{"key":"697eb2550729a10ce9f1feb05a88200c975665a1-51","descr":"Post-judgment interest","amount":0.06},{"key":"697eb2550729a10ce9f1feb05a88200c975665a1-52","descr":"Post-judgment interest","amount":0.06},{"key":"697eb2550729a10ce9f1feb05a88200c975665a1-53","descr":"Post-judgment interest","amount":0.06},{"key":"697eb2550729a10ce9f1feb05a88200c975665a1-54","descr":"Post-judgment interest","amount":0.06},{"key":"697eb2550729a10ce9f1feb05a88200c975665a1-55","descr":"Post-judgment interest","amount":0.06},{"key":"697eb2550729a10ce9f1feb05a88200c975665a1-56","descr":"Post-judgment interest","amount":0.06},{"key":"697eb2550729a10ce9f1feb05a88200c975665a1-57","descr":"Post-judgment interest","amount":0.06},{"key":"697eb2550729a10ce9f1feb05a88200c975665a1-58","descr":"Post-judgment interest","amount":0.06},{"key":"697eb2550729a10ce9f1feb05a88200c975665a1-59","descr":"Post-judgment interest","amount":0.06},{"key":"697eb2550729a10ce9f1feb05a88200c975665a1-60","descr":"Post-judgment interest","amount":0.06},{"key":"697eb2550729a10ce9f1feb05a88200c975665a1-61","descr":"Post-judgment interest","amount":0.06},{"key":"697eb2550729a10ce9f1feb05a88200c975665a1-62","descr":"Post-judgment interest","amount":0.06},{"key":"697eb2550729a10ce9f1feb05a88200c975665a1-63","descr":"Post-judgment interest","amount":0.06},{"key":"697eb2550729a10ce9f1feb05a88200c975665a1-64","descr":"Post-judgment interest","amount":0.06},{"key":"697eb2550729a10ce9f1feb05a88200c975665a1-65","descr":"Post-judgment interest","amount":0.06},{"key":"697eb2550729a10ce9f1feb05a88200c975665a1-66","descr":"Post-judgment interest","amount":0.06},{"key":"697eb2550729a10ce9f1feb05a88200c975665a1-67","descr":"Post-judgment interest","amount":0.06},{"key":"697eb2550729a10ce9f1feb05a88200c975665a1-68","descr":"Post-judgment interest","amount":0.06},{"key":"697eb2550729a10ce9f1feb05a88200c975665a1-69","descr":"Post-judgment interest","amount":0.06},{"key":"697eb2550729a10ce9f1feb05a88200c975665a1-70","descr":"Post-judgment interest","amount":0.06},{"key":"697eb2550729a10ce9f1feb05a88200c975665a1-71","descr":"Post-judgment interest","amount":0.06},{"key":"697eb2550729a10ce9f1feb05a88200c975665a1-72","descr":"Post-judgment interest","amount":0.06},{"key":"697eb2550729a10ce9f1feb05a88200c975665a1-73","descr":"Post-judgment interest","amount":0.06},{"key":"697eb2550729a10ce9f1feb05a88200c975665a1-74","descr":"Post-judgment interest","amount":0.06},{"key":"697eb2550729a10ce9f1feb05a88200c975665a1-75","descr":"Post-judgment interest","amount":0.06},{"key":"697eb2550729a10ce9f1feb05a88200c975665a1-76","descr":"Post-judgment interest","amount":0.06},{"key":"697eb2550729a10ce9f1feb05a88200c975665a1-77","descr":"Post-judgment interest","amount":0.06},{"key":"697eb2550729a10ce9f1feb05a88200c975665a1-78","descr":"Post-judgment interest","amount":0.06}]}],"branchId":null,"documents":[],"wcisClsCode":"Resisting Officer","tac":null,"countyNo":53,"charges":[{"judgments":[{"supervisions":[{"superMiscConds":[],"descr":"Costs","key":"53-2015CM001960-1-1-1","notes":null,"time":null,"isShowConds":false,"superTimeConds":[],"beginDate":null},{"superMiscConds":[],"descr":"Local Jail","key":"53-2015CM001960-1-1-2","notes":"w/Huber; Concurrent with Count 2 and with 15CM154; COURT STAYS SENTENCE FOR 4 DAYS. MUST REPORT 11-03-2015 AT 7AM.  May have Diversion.","time":"6 Months","isShowConds":false,"superTimeConds":[],"beginDate":"2015-11-03"}],"orderDate":"2015-10-30","isModified":false,"superAgency":null,"miscConds":[],"key":"53-2015CM001960-1-1","dispoCtofc":"Haakenson, Michael A.","timeConds":[],"dispoDesc":null,"probByCase":null,"sentDate":"2015-10-30","isConverted":false,"reOpenedEvent":null,"action":"Guilty Due to No Contest Plea"}],"pleaDate":"2015-10-30","descr":"Obstructing an Officer","offenseDate":"2015-09-23","id":"53-2015CM001960-1","pleaDescr":"No Contest","chargeModifiers":[],"dispoDesc":"Guilty Due to No Contest Plea","statuteCite":"946.41(1)","severity":"Misd. A","chargeNo":1,"isSummaryCandidate":true},{"judgments":[{"supervisions":[{"superMiscConds":[],"descr":"Costs","key":"53-2015CM001960-2-1-1","notes":null,"time":null,"isShowConds":false,"superTimeConds":[],"beginDate":null},{"superMiscConds":[],"descr":"Local Jail","key":"53-2015CM001960-2-1-2","notes":"w/Huber; Concurrent with Count 1","time":"6 Months","isShowConds":false,"superTimeConds":[],"beginDate":"2015-11-03"}],"orderDate":"2015-10-30","isModified":false,"superAgency":null,"miscConds":[],"key":"53-2015CM001960-2-1","dispoCtofc":"Haakenson, Michael A.","timeConds":[],"dispoDesc":null,"probByCase":null,"sentDate":"2015-10-30","isConverted":false,"reOpenedEvent":null,"action":"Guilty Due to No Contest Plea"}],"pleaDate":"2015-10-30","descr":"Carry Concealed Weapon","offenseDate":"2015-09-23","id":"53-2015CM001960-2","pleaDescr":"No Contest","chargeModifiers":[],"dispoDesc":"Guilty Due to No Contest Plea","statuteCite":"941.23(2)","severity":"Misd. A","chargeNo":2,"isSummaryCandidate":true}],"crossReferenced":[],"caption":"State of Wisconsin vs. Kevin Lee Holton","status":"Closed","filingDate":"2015-09-25","defendant":{"attys":[{"name":"Lantta, Matt","withdrawn":null,"key":"53-2015CM001960-1-1093139-2015-10-05","isGal":false,"entered":"2015-10-05"}],"name":"Holton, Kevin Lee","partyNo":1,"dob":"1991-07-16","fingerprintId":null,"inclGal":false,"effDate":"2019-05-03","sex":"Male","alias":[],"race":"Caucasian","status":null,"address":"2139 Lenox Street, Beloit, WI 53511","type":"Defendant","justisNo":null,"sealed":false},"respCtofc":"Haakenson, Michael A.","available":true,"isCriminal":true,"caseType":"CM","records":[{"addlTxt":"ADDRESS INFO for Kevin Lee Holton\nCurrent: 2139 Lenox Street, Beloit, WI 53511 United States  (Effective: 05-03-2019)\nPrior: 1157 Forest Ave., Beloit, WI 53511 \n","parties":[{"sealed":false,"name":"Holton, Kevin Lee"}],"descr":"Change of address notification","amount":null,"key":"53-2015CM001960-19","ctofc":null,"date":"2019-05-03","courtRptr":null},{"addlTxt":null,"parties":[],"descr":"Actual bond posted with sheriff","amount":636.00,"key":"53-2015CM001960-18","ctofc":null,"date":"2017-12-14","courtRptr":null},{"addlTxt":"modified to zero - commitment served 12/10/17 - copy filed 12/11/17","parties":[{"sealed":false,"name":"Holton, Kevin Lee"}],"descr":"Warrant/Capias/Commitment served","amount":null,"key":"53-2015CM001960-17","ctofc":null,"date":"2017-12-11","courtRptr":null},{"addlTxt":null,"parties":[],"descr":"Records of prosec. are converted data. See file.","amount":null,"key":"53-2015CM001960-16","ctofc":null,"date":"2017-11-15","courtRptr":null},{"addlTxt":null,"parties":[],"descr":"Judgment for unpaid fine/forfeiture/other","amount":15.00,"key":"53-2015CM001960-15","ctofc":null,"date":"2016-04-26","courtRptr":null},{"addlTxt":null,"parties":[],"descr":"Judgment for unpaid fine/forfeiture/other","amount":886.00,"key":"53-2015CM001960-14","ctofc":null,"date":"2016-04-26","courtRptr":null},{"addlTxt":null,"parties":[{"sealed":false,"name":"Holton, Kevin Lee"}],"descr":"Commitment issued","amount":886.00,"key":"53-2015CM001960-13","ctofc":"Haakenson, Michael A.","date":"2016-04-26","courtRptr":null},{"addlTxt":null,"parties":[],"descr":"Deferred payment agreement","amount":null,"key":"53-2015CM001960-12","ctofc":null,"date":"2016-02-23","courtRptr":null},{"addlTxt":null,"parties":[],"descr":"Judgment of conviction","amount":null,"key":"53-2015CM001960-10","ctofc":"Haakenson, Michael A.","date":"2015-11-02","courtRptr":null},{"addlTxt":null,"parties":[],"descr":"Demand for discovery","amount":null,"key":"53-2015CM001960-11","ctofc":null,"date":"2015-10-30","courtRptr":null},{"addlTxt":null,"parties":[],"descr":"Plea questionnaire, waiver of rights","amount":null,"key":"53-2015CM001960-9","ctofc":null,"date":"2015-10-30","courtRptr":null},{"addlTxt":null,"parties":[],"descr":"Dispositional order/judgment","amount":null,"key":"53-2015CM001960-8","ctofc":"Haakenson, Michael A.","date":"2015-10-30","courtRptr":null},{"addlTxt":"Defendant Kevin Lee Holton in court in custody with attorney Matthew Lantta.  Anne Theresa Nack appeared for the State of Wisconsin. Deft pleads No Contest freely and voluntarily; Court accepts plea and finds Deft Guilty; Court orders: 6 months RCJail, each count Concurrent; w/Huber; Concurrent with 15CM154; $886 costs ex to 01-07-16; Court STAYS SENTENCE FOR 4 DAYS.  MUST REPORT TO JAIL 11-03-2015 AT 7AM.  Diversion program. 37 days Credit.","parties":[],"descr":"Plea/sentencing hearing","amount":null,"key":"53-2015CM001960-7","ctofc":"Haakenson, Michael A.","date":"2015-10-30","courtRptr":"Mueller, Tammie"},{"addlTxt":"Status conference at 10-30-2015 11:00 am","parties":[],"descr":"Notice of hearing","amount":null,"key":"53-2015CM001960-6","ctofc":null,"date":"2015-10-08","courtRptr":null},{"addlTxt":null,"parties":[],"descr":"Demand for discovery and inspection","amount":null,"key":"53-2015CM001960-5","ctofc":null,"date":"2015-10-05","courtRptr":null},{"addlTxt":"M Lantta","parties":[],"descr":"Public defender order appointing counsel","amount":null,"key":"53-2015CM001960-4","ctofc":null,"date":"2015-10-05","courtRptr":null},{"addlTxt":"Defendant Kevin Lee Holton in court in custody with attorney Ashley Jade Morse.  Mark M. Jahnke appeared for the State of Wisconsin.  Complaint filed, copy to Defendant, penalties advised, rights given, reading waived.  Defendant stands mute, not guilty plea entered by Court, jury trial to be set.","parties":[],"descr":"Initial appearance","amount":null,"key":"53-2015CM001960-3","ctofc":"Meyer, Stephen D.","date":"2015-09-25","courtRptr":"Hill, Kristen Lee"},{"addlTxt":"Not to poss any firearms/weapons","parties":[{"sealed":false,"name":"Holton, Kevin Lee"}],"descr":"Signature bond set","amount":500.00,"key":"53-2015CM001960-2","ctofc":null,"date":"2015-09-25","courtRptr":null},{"addlTxt":null,"parties":[],"descr":"Complaint filed","amount":null,"key":"53-2015CM001960-1","ctofc":"Meyer, Stephen D.","date":"2015-09-25","courtRptr":null}],"prosAgency":"District Attorney","citations":[],"defAttys":[{"name":"Lantta, Matt"}],"balanceDue":85.09,"allowPurchase":false},"view":{"caseNo":{"value":"2015CM001960"},"countyNo":{"value":53}}}